terminal_colors/__init__.py
terminal_colors_lld-1.0.0.dist-info/licenses/LICENCE
terminal_colors_lld-1.0.0.dist-info/METADATA
terminal_colors_lld-1.0.0.dist-info/WHEEL
terminal_colors_lld-1.0.0.dist-info/top_level.txt
terminal_colors_lld-1.0.0.dist-info/RECORD
