Metadata-Version: 2.4
Name: terminal_colors_LLD
Version: 1.0.0
Summary: A package for coloring your output to the terminal
Author: LLD
Author-email: LLD <lduinker04@gmail.com>
License-Expression: MIT
Classifier: Programming Language :: Python :: 3
Classifier: Operating System :: OS Independent
Requires-Python: >=3.13
License-File: LICENCE
Dynamic: author
Dynamic: license-file
